pyfipe/__init__.py
pyfipe/_modidx.py
pyfipe/core.py
pyfipe/tabelas.py
pyfipe-0.0.2.dist-info/LICENSE
pyfipe-0.0.2.dist-info/METADATA
pyfipe-0.0.2.dist-info/WHEEL
pyfipe-0.0.2.dist-info/entry_points.txt
pyfipe-0.0.2.dist-info/top_level.txt
pyfipe-0.0.2.dist-info/RECORD
